{
    "ir": true,
    "ir_value": 1,
    "flood_light": false,
    "flood_light_intensity": 1,
    "stereoResolution": {"x": 1280, "y": 800},
    "rgbResolution": {"x": 640, "y": 480},
    "monoSettings": {
        "luma_denoise": 1,
        "sharpness": 2,
        "contrast": 0
    },

    "output_settings": {
        "left": true,
        "right": true,
        "rgb": true,
        "depth": true,
        "disparity": true,
        "sync": true
    },

    "profilePreset": "DEFAULT",
    "LRcheck": true,
    "extendedDisparity": true,

    "FPS": 5,
    "num_captures": 20
}
